{"blog-sidebar":{"search-2":{"title":"Search Here"},"tp-latest-posts-2":{"title":"Recent Post","count":"3","posts_order":"DESC"},"categories-2":{"title":"Categories","count":0,"hierarchical":0,"dropdown":0},"tag_cloud-2":{"title":"Tags","count":0,"taxonomy":"post_tag"}},"footer-1":{"custom_html-2":{"title":"","content":"\r\n                     <div class=\"tp-footer-widget__logo mb-30\">\r\n                        <a href=\"https:\/\/weblearnbd.net\/wp\/collax\/\"><img src=\"https:\/\/weblearnbd.net\/wp\/collax\/wp-content\/uploads\/2022\/08\/logo-white.png\" alt=\"\"><\/a>\r\n                     <\/div>\r\n                     <div class=\"tp-footer-widget__text mb-30\">\r\n                        <p>A new way to make the payments easy,\r\n                           reliable and 100% secure. claritatem itamconse quat. Exerci tationulla<\/p>\r\n                     <\/div>\r\n                     <div class=\"tp-footer-widget__social-link\">\r\n                        <a href=\"#\"><i class=\"fab fa-youtube\"><\/i><\/a>\r\n                        <a href=\"#\"><i class=\"fab fa-twitter\"><\/i><\/a>\r\n                        <a href=\"#\"><i class=\"fab fa-facebook-f\"><\/i><\/a>\r\n                        <a href=\"#\"><i class=\"fab fa-skype\"><\/i><\/a>\r\n                     <\/div>"}},"footer-2":{"nav_menu-2":{"title":"Useful Links","nav_menu":19}},"footer-3":{"nav_menu-3":{"title":"Community","nav_menu":20}},"footer-4":{"custom_html-3":{"title":"Subscribe Newslatter","content":"<div class=\"tp-footer-widget__text mb-55\">\r\n                        <p>Exerci tation ullamcorper suscipit lobortis nisl aliquip ex ea commodo<\/p>\r\n                     <\/div><div class=\"tp-footer-widget__input\">\r\n                        <form action=\"#\">\r\n                           <input type=\"text\" placeholder=\"Enter Mail\">\r\n                           <button type=\"submit\"><i class=\"fas fa-paper-plane\"><\/i><\/button>\r\n                        <\/form>\r\n                     <\/div>"}},"footer-4-1":{"custom_html-4":{"title":"","content":"\r\n                     <div class=\"tp-footer-widget__logo mb-30\">\r\n                        <a href=\"https:\/\/weblearnbd.net\/wp\/collax\/\"><img src=\"https:\/\/weblearnbd.net\/wp\/collax\/wp-content\/themes\/collax\/assets\/img\/logo\/logo-blue.png\" alt=\"\"><\/a>\r\n                     <\/div>\r\n                     <div class=\"tp-footer-widget__text mb-30\">\r\n                        <p>A new way to make the payments easy,\r\n                           reliable and 100% secure. claritatem itamconse quat. Exerci tationulla<\/p>\r\n                     <\/div>\r\n                     <div class=\"tp-footer-widget__social-link tp-footer-widget__social-link-2 \">\r\n                        <a href=\"#\"><i class=\"fab fa-youtube\"><\/i><\/a>\r\n                        <a href=\"#\"><i class=\"fab fa-twitter\"><\/i><\/a>\r\n                        <a href=\"#\"><i class=\"fab fa-facebook-f\"><\/i><\/a>\r\n                        <a href=\"#\"><i class=\"fab fa-skype\"><\/i><\/a>\r\n                     <\/div>"}},"footer-4-2":{"nav_menu-4":{"title":"Useful Links","nav_menu":19}},"footer-4-3":{"nav_menu-5":{"title":"Community","nav_menu":20}},"footer-4-4":{"custom_html-5":{"title":"Subscribe Newslatter","content":"<div class=\"tp-footer-widget__text mb-55\">\r\n                        <p>Exerci tation ullamcorper suscipit lobortis nisl aliquip ex ea commodo<\/p>\r\n                     <\/div><div class=\"tp-footer-widget__input tp-input-white\">\r\n                        <form action=\"#\">\r\n                           <input type=\"text\" placeholder=\"Enter Mail\">\r\n                           <button type=\"submit\"><i class=\"fas fa-paper-plane\"><\/i><\/button>\r\n                        <\/form>\r\n                     <\/div>"}}}